{
  "updatedAt": "2026-05-02T06:00:49.656Z",
  "strava": {
    "streakWeeks": 27,
    "sessionsThisYear": 132,
    "lastRun": {
      "weekday": "Wednesday",
      "km": 6,
      "isoDate": "2026-04-29"
    },
    "weeklyKmLast12": [
      42.4,
      19.3,
      30.8,
      23,
      9.1,
      29.3,
      13.2,
      114.4,
      7.5,
      27.6,
      73.5,
      48.2
    ]
  },
  "github": {
    "commits30d": 98,
    "latestRepo": {
      "name": "NewPortfolioSite",
      "url": "https://github.com/richter-max/NewPortfolioSite",
      "pushedAt": "2026-04-14T13:15:14Z",
      "headline": "Auto-generated changes",
      "commitDate": "2026-04-14T13:15:13Z"
    }
  }
}
