{
  "updatedAt": "2026-05-09T06:09:39.768Z",
  "strava": {
    "streakWeeks": 28,
    "sessionsThisYear": 141,
    "lastRun": {
      "weekday": "Tuesday",
      "km": 7.1,
      "isoDate": "2026-05-05"
    },
    "weeklyKmLast12": [
      19.3,
      30.8,
      23,
      9.1,
      29.3,
      13.2,
      114.4,
      7.5,
      27.6,
      73.5,
      73.2,
      8
    ]
  },
  "github": {
    "commits30d": 110,
    "latestRepo": {
      "name": "PortfolioSite",
      "url": "https://github.com/richter-max/PortfolioSite",
      "pushedAt": "2026-05-08T05:51:23Z",
      "headline": "chore: refresh live stats (2026-05-08)",
      "commitDate": "2026-05-08T05:51:22Z"
    }
  }
}
